antupy/__init__.py
antupy/analyser/__init__.py
antupy/analyser/par.py
antupy/core/__init__.py
antupy/core/array.py
antupy/core/frame.py
antupy/core/plant.py
antupy/core/units.py
antupy/core/var.py
antupy/ddd.py
antupy/ddd_au.py
antupy/ddd_cl.py
antupy/protocols.py
antupy/py.typed
antupy/tsg/__init__.py
antupy/tsg/mkt.py
antupy/tsg/settings.py
antupy/tsg/weather.py
antupy/utils/htc.py
antupy/utils/loc/__init__.py
antupy/utils/loc/loc.py
antupy/utils/loc/loc_au.py
antupy/utils/loc/loc_cl.py
antupy/utils/props.py
antupy/utils/solar.py
antupy-0.5.0.dist-info/LICENSE
antupy-0.5.0.dist-info/METADATA
antupy-0.5.0.dist-info/WHEEL
antupy-0.5.0.dist-info/RECORD
