Metadata-Version: 2.3
Name: antupy
Version: 0.5.0
Summary: Toolkit for energy engineering
License: MIT
Author: David Saldivia
Author-email: david.saldivia.s@gmail.com
Requires-Python: >=3.12,<3.14
Classifier: License :: OSI Approved :: MIT License
Classifier: Programming Language :: Python :: 3
Classifier: Programming Language :: Python :: 3.12
Classifier: Programming Language :: Python :: 3.13
Requires-Dist: coolprop (>=6.8.0,<7.0.0)
Requires-Dist: matplotlib (>=3.9.2,<4.0.0)
Requires-Dist: numpy (>=2.1.2,<3.0.0)
Requires-Dist: pandas (>=2.2.3,<3.0.0)
Requires-Dist: polars (>=1.9.0,<2.0.0)
Requires-Dist: pvlib (>=0.11.1,<0.12.0)
Requires-Dist: scipy (>=1.14.1,<2.0.0)
Requires-Dist: xarray (>=2025.9.0,<2026.0.0)
Project-URL: Homepage, https://github.com/DavidSaldivia/antupy
Project-URL: Repository, https://github.com/DavidSaldivia/antupy
